{
	"format_version": "1.8.0",
	"animations": {
		"static_idle": {
			"loop": true,
			"animation_length": 0.0833,
			"bones": {
				"left": {
					"rotation": [96.65895, 31.60263, 42.57262],
					"position": [8, -12, -4],
					"scale": [1, 1.5, 1]
				},
				"right": {
					"rotation": [85, 0, 0],
					"position": [-6, -16, 9],
					"scale": [1, 1.5, 1]
				}
			}
		},
		"put_away": {
			"loop": true,
			"animation_length": 1.375,
			"bones": {
				"root": {
					"rotation": {
						"0.0": [0, 0, 2.5],
						"1.125": [-360, 7.5, -357.5],
						"1.3333": {"pre": [-360, 7.5, -357.5], "post": [0, 0, 2.5]}
					},
					"position": {
						"0.0": [0, 0, 0],
						"0.9583": [0, -66, 0],
						"1.125": [0, -38.9375, 0],
						"1.3333": {"pre": [0, -38.9375, 0], "post": [0, -91, 0]}
					}
				},
				"left": {
					"rotation": [96.65895, 31.60263, 42.57262],
					"position": [8, -12, -4],
					"scale": [1, 1.5, 1]
				},
				"constraint": {
					"rotation": [0, 0, -2.5]
				},
				"right": {
					"rotation": [85, 0, 0],
					"position": [-6, -16, 9],
					"scale": [1, 1.5, 1]
				},
				"lefthand_and_mag": {
					"rotation": {
						"0.0": [0, 0, 0],
						"1.1667": [0, 1830, 0]
					}
				}
			},
			"sound_effects": {
				"0.0": {
					"effect": "put_away.mp3"
				}
			}
		},
		"draw": {
			"loop": true,
			"animation_length": 2.9583,
			"bones": {
				"root": {
					"rotation": {
						"0.0": {
							"post": [-632.75806, -24.97457, -86.33476],
							"lerp_mode": "catmullrom"
						},
						"0.375": {
							"post": [-379.29236, -5.99446, 699.21736],
							"lerp_mode": "catmullrom"
						},
						"0.75": {
							"post": [0, 0, 2.5],
							"lerp_mode": "catmullrom"
						},
						"1.375": {
							"post": [-34.23216, -47.13536, 29.00648],
							"lerp_mode": "catmullrom"
						},
						"1.9583": {
							"post": [-32.01011, -43.78426, 25.89065],
							"lerp_mode": "catmullrom"
						},
						"2.0833": {
							"post": [-34.38509, 40.28499, -1088.98682],
							"lerp_mode": "catmullrom"
						},
						"2.4583": {
							"post": [0, 0, 0],
							"lerp_mode": "catmullrom"
						}
					},
					"position": {
						"0.0": {
							"post": [0, -36, 0],
							"lerp_mode": "catmullrom"
						},
						"0.1667": {
							"post": [0, 20.86, 0],
							"lerp_mode": "catmullrom"
						},
						"0.375": {
							"post": [0, -29.89, 0],
							"lerp_mode": "catmullrom"
						},
						"0.5833": {
							"post": [0, -4.54, 0],
							"lerp_mode": "catmullrom"
						},
						"0.9167": {
							"post": [0, 0, 0],
							"lerp_mode": "catmullrom"
						}
					}
				},
				"left": {
					"rotation": [96.65895, 31.60263, 42.57262],
					"position": [8, -12, -4],
					"scale": [1, 1.5, 1]
				},
				"constraint": {
					"rotation": [0, 0, -2.5]
				},
				"right": {
					"rotation": [85, 0, 0],
					"position": [-6, -16, 9],
					"scale": [1, 1.5, 1]
				}
			},
			"sound_effects": {
				"0.0": {
					"effect": "draw.mp3"
				}
			}
		},
		"reload_tactical": {
			"loop": true,
			"animation_length": 5.375,
			"bones": {
				"root": {
					"rotation": {
						"0.0": {
							"post": [0, 0, 2.5],
							"lerp_mode": "catmullrom"
						},
						"0.0417": {
							"post": [-556.15359, -51.3798, 375.25141],
							"lerp_mode": "catmullrom"
						},
						"0.0833": {
							"post": [-750.98238, -14.3042, 367.70206],
							"lerp_mode": "catmullrom"
						},
						"1.2917": {
							"post": [-750.68108, -12.15741, 366.3859],
							"lerp_mode": "catmullrom"
						},
						"1.7917": {
							"post": [-731.05776, -12.15741, 366.3859],
							"lerp_mode": "catmullrom"
						},
						"2.1667": {
							"post": [-360, -12.5, -357.5],
							"lerp_mode": "catmullrom"
						},
						"3.2083": {
							"post": [-274.05694, -1.87889, -217.84706],
							"lerp_mode": "catmullrom"
						},
						"4.0417": {
							"post": [0, 0, 2.5],
							"lerp_mode": "catmullrom"
						}
					},
					"position": {
						"0.0": {
							"post": [0, 0, 0],
							"lerp_mode": "catmullrom"
						},
						"0.0417": {
							"post": [1, 1, 0],
							"lerp_mode": "catmullrom"
						},
						"0.3333": {
							"post": [-1.9, 0.46, 0],
							"lerp_mode": "catmullrom"
						},
						"0.5833": {
							"post": [1.1875, 0, 0],
							"lerp_mode": "catmullrom"
						},
						"1.25": {
							"post": [0.7525, 0, 0],
							"lerp_mode": "catmullrom"
						},
						"1.6667": {
							"post": [0, 1, 0],
							"lerp_mode": "catmullrom"
						},
						"2.4167": {
							"post": [0, 0, 0],
							"lerp_mode": "catmullrom"
						},
						"4.6667": {
							"post": [0, 0, 0],
							"lerp_mode": "catmullrom"
						}
					}
				},
				"left": {
					"rotation": {
						"0.0": [96.65895, 31.60263, 42.57262],
						"0.0833": [1777.73066, -24.6853, -1190.09231],
						"0.8333": [1777.73066, -24.6853, -1190.09231],
						"2.5417": [96.65895, 31.60263, 42.57262]
					},
					"position": [8, -12, -4],
					"scale": [1, 1.5, 1]
				},
				"right": {
					"rotation": {
						"0.0": [85, 0, 0],
						"0.8333": [1777.73066, -24.6853, -1190.09231],
						"2.5417": [96.65895, 31.60263, 42.57262]
					},
					"position": [-6, -16, 9],
					"scale": [1, 1.5, 1]
				},
				"lefthand_and_mag": {
					"rotation": {
						"0.0833": [0, 0, 0],
						"0.125": [-615, 0, 0],
						"0.375": [-615, 0, 0],
						"1.0417": [-693.16317, -73.40211, 1332.51385],
						"1.25": [-615, 0, 0],
						"1.4167": [0, 0, 0]
					},
					"position": {
						"0.0833": [0, -3, 0],
						"0.125": [4, -6, 0],
						"0.375": [4, -6, 0],
						"0.4583": [9, -8, -9],
						"0.7083": [9, -8, -9],
						"1.25": [4, -6, 0],
						"1.4167": [0, 0, 0]
					}
				}
			},
			"sound_effects": {
				"0.0": {
					"effect": ".mp3"
				}
			}
		},
		"reload_empty": {
			"loop": true,
			"animation_length": 6.625,
			"bones": {
				"root": {
					"rotation": {
						"0.0": {
							"post": [0, 0, 2.5],
							"lerp_mode": "catmullrom"
						},
						"0.0417": {
							"post": [-556.15359, -51.3798, 375.25141],
							"lerp_mode": "catmullrom"
						},
						"0.0833": {
							"post": [-750.98238, -14.3042, 367.70206],
							"lerp_mode": "catmullrom"
						},
						"1.2917": {
							"post": [-750.68108, -12.15741, 366.3859],
							"lerp_mode": "catmullrom"
						},
						"1.7917": {
							"post": [-731.05776, -12.15741, 366.3859],
							"lerp_mode": "catmullrom"
						},
						"2.1667": {
							"post": [-360, -12.5, -357.5],
							"lerp_mode": "catmullrom"
						},
						"3.25": {
							"post": [0, 0, 2.5],
							"lerp_mode": "catmullrom"
						},
						"3.7083": {
							"post": [-39.23152, 37.76124, 35.93495],
							"lerp_mode": "catmullrom"
						},
						"4.5417": {
							"post": [356.90014, 74.2705, -100.85878],
							"lerp_mode": "catmullrom"
						},
						"4.875": {
							"post": [0, 0, 2.5],
							"lerp_mode": "catmullrom"
						},
						"5.2917": {
							"post": [60.92783, 2.54506, -820.17232],
							"lerp_mode": "catmullrom"
						},
						"5.875": {
							"post": [206.27576, 52.82259, -172.24165],
							"lerp_mode": "catmullrom"
						},
						"6.5417": {
							"post": [0, 0, 2.5],
							"lerp_mode": "catmullrom"
						}
					},
					"position": {
						"0.0": {
							"post": [0, 0, 0],
							"lerp_mode": "catmullrom"
						},
						"0.0417": {
							"post": [1, 1, 0],
							"lerp_mode": "catmullrom"
						},
						"0.3333": {
							"post": [-1.9, 0.46, 0],
							"lerp_mode": "catmullrom"
						},
						"0.5833": {
							"post": [1.1875, 0, 0],
							"lerp_mode": "catmullrom"
						},
						"1.25": {
							"post": [0.7525, 0, 0],
							"lerp_mode": "catmullrom"
						},
						"1.6667": {
							"post": [0, 1, 0],
							"lerp_mode": "catmullrom"
						},
						"2.4167": {
							"post": [0, 0, 0],
							"lerp_mode": "catmullrom"
						},
						"3.875": {
							"post": [0, 0, 0],
							"lerp_mode": "catmullrom"
						},
						"5.0833": {
							"post": [11, -1, -5],
							"lerp_mode": "catmullrom"
						},
						"5.5": {
							"post": [-6, 0, -3],
							"lerp_mode": "catmullrom"
						},
						"6.4583": {
							"post": [0, 0, 0],
							"lerp_mode": "catmullrom"
						}
					}
				},
				"left": {
					"rotation": {
						"0.0": [96.65895, 31.60263, 42.57262],
						"0.0833": [1777.73066, -24.6853, -1190.09231],
						"0.8333": [1777.73066, -24.6853, -1190.09231],
						"2.5417": [96.65895, 31.60263, 42.57262]
					},
					"position": [8, -12, -4],
					"scale": [1, 1.5, 1]
				},
				"right": {
					"rotation": {
						"0.0": [85, 0, 0],
						"2.5": [1777.73066, -24.6853, -1190.09231],
						"4.2083": [96.65895, 31.60263, 42.57262]
					},
					"position": {
						"0.0": [-6, -16, 9],
						"2.5": [-6, -16, 9],
						"3.625": [-8.8125, -9.9375, -0.625],
						"3.7917": [-8.81, -9.94, 10.38],
						"4.0417": [-8.81, -9.94, 16.38]
					},
					"scale": [1, 1.5, 1]
				},
				"lefthand_and_mag": {
					"rotation": {
						"0.0833": [0, 0, 0],
						"0.125": [-615, 0, 0],
						"0.375": [-615, 0, 0],
						"1.0417": [-693.16317, -73.40211, 1332.51385],
						"1.25": [-615, 0, 0],
						"1.4167": [0, 0, 0],
						"3.9167": [0, 0, 0],
						"5.625": [1202.5, 0, 0],
						"6.4583": [0, 0, 0]
					},
					"position": {
						"0.0833": [0, -3, 0],
						"0.125": [4, -6, 0],
						"0.375": [4, -6, 0],
						"0.4583": [9, -8, -9],
						"0.7083": [9, -8, -9],
						"1.25": [4, -6, 0],
						"1.4167": [0, 0, 0],
						"5.2083": [0, 0, 0]
					}
				}
			},
			"sound_effects": {
				"0.0": {
					"effect": ".mp3"
				}
			}
		},
		"inspect": {
			"loop": true,
			"animation_length": 8.4583,
			"bones": {
				"root": {
					"rotation": {
						"0.0": {
							"post": [0, 0, 2.5],
							"lerp_mode": "catmullrom"
						},
						"0.0417": {
							"post": [-776.14245, -14.25404, 1108.89135],
							"lerp_mode": "catmullrom"
						},
						"0.1667": {
							"post": [37.14529, -30.60802, -70.88992],
							"lerp_mode": "catmullrom"
						},
						"0.4167": {
							"post": [45.32384, -26.80832, -74.59681],
							"lerp_mode": "catmullrom"
						},
						"0.625": {
							"post": [-59.67616, -26.80832, -74.59681],
							"lerp_mode": "catmullrom"
						},
						"0.9583": {
							"post": [45.32384, -26.80832, -74.59681],
							"lerp_mode": "catmullrom"
						},
						"1.0": {
							"post": [-776.14245, -14.25404, 1108.89135],
							"lerp_mode": "catmullrom"
						},
						"1.0417": {
							"post": [45.32384, -26.80832, -74.59681],
							"lerp_mode": "catmullrom"
						},
						"1.0833": {
							"post": [-28.29773, 24.94219, 424.74059],
							"lerp_mode": "catmullrom"
						},
						"1.375": {
							"post": [-185.70715, 6.26262, 222.1569],
							"lerp_mode": "catmullrom"
						},
						"1.5833": {
							"post": [-41.46762, 48.91408, 21.23279],
							"lerp_mode": "catmullrom"
						},
						"1.7917": {
							"post": [-59.67616, -26.80832, -74.59681],
							"lerp_mode": "catmullrom"
						},
						"1.8333": {
							"post": [45.32384, -26.80832, -74.59681],
							"lerp_mode": "catmullrom"
						},
						"1.9583": {
							"post": [-31.56513, 37.21161, 32.94231],
							"lerp_mode": "catmullrom"
						},
						"2.0417": {
							"post": [45.32384, -26.80832, -74.59681],
							"lerp_mode": "catmullrom"
						},
						"2.1667": {
							"post": [-31.56513, 37.21161, 32.94231],
							"lerp_mode": "catmullrom"
						},
						"2.5417": {
							"post": [-26.36583, 19.55395, 43.87308],
							"lerp_mode": "catmullrom"
						},
						"2.75": {
							"post": [-28.91492, 30.36006, 37.71897],
							"lerp_mode": "catmullrom"
						},
						"2.9583": {
							"post": [43.58508, 30.36006, 37.71897],
							"lerp_mode": "catmullrom"
						},
						"3.0417": {
							"post": [-776.14245, -14.25404, 1108.89135],
							"lerp_mode": "catmullrom"
						},
						"3.2083": {
							"post": [0, 0, 2.5],
							"lerp_mode": "catmullrom"
						},
						"3.3333": {
							"post": [-776.14245, -14.25404, 1108.89135],
							"lerp_mode": "catmullrom"
						},
						"3.5": {
							"post": [0, 0, 2.5],
							"lerp_mode": "catmullrom"
						},
						"3.7083": {
							"post": [0, 0, 2.5],
							"lerp_mode": "catmullrom"
						},
						"3.7917": {
							"post": [-776.14245, -14.25404, 1108.89135],
							"lerp_mode": "catmullrom"
						},
						"3.875": {
							"post": [0, 0, 2.5],
							"lerp_mode": "catmullrom"
						},
						"4.25": {
							"post": [-180, -35, -177.5],
							"lerp_mode": "catmullrom"
						},
						"4.7083": {
							"post": [-657.5, 0, 2.5],
							"lerp_mode": "catmullrom"
						},
						"5.25": {
							"post": [-180, -35, -177.5],
							"lerp_mode": "catmullrom"
						},
						"5.7083": {
							"post": [0, 0, 2.5],
							"lerp_mode": "catmullrom"
						},
						"6.2083": {
							"post": [0, 0, 2.5],
							"lerp_mode": "catmullrom"
						},
						"6.2917": {
							"post": [-776.14245, -14.25404, 1108.89135],
							"lerp_mode": "catmullrom"
						},
						"6.375": {
							"post": [0, 0, 2.5],
							"lerp_mode": "catmullrom"
						},
						"6.5417": {
							"post": [0, 0, 2.5],
							"lerp_mode": "catmullrom"
						},
						"6.75": {
							"post": [-15, 0, 7.5],
							"lerp_mode": "catmullrom"
						},
						"7.2917": {
							"post": [0, 0, 2.5],
							"lerp_mode": "catmullrom"
						},
						"7.5833": {
							"post": [145.98062, 29.36734, 111.12959],
							"lerp_mode": "catmullrom"
						},
						"8.75": {
							"post": [0, 0, 2.5],
							"lerp_mode": "catmullrom"
						}
					},
					"position": {
						"0.0": {
							"post": [0, 0, 0],
							"lerp_mode": "catmullrom"
						},
						"0.0417": {
							"post": [0, 1.625, 0],
							"lerp_mode": "catmullrom"
						},
						"0.1667": {
							"post": [10.875, 2.88, -27],
							"lerp_mode": "catmullrom"
						},
						"0.4167": {
							"post": [1.39563, 2.88, 0],
							"lerp_mode": "catmullrom"
						},
						"0.625": {
							"post": [1.04062, 2.88, 0],
							"lerp_mode": "catmullrom"
						},
						"0.9583": {
							"post": [1.39563, 2.88, 0],
							"lerp_mode": "catmullrom"
						},
						"1.0": {
							"post": [0, 1.625, 0],
							"lerp_mode": "catmullrom"
						},
						"1.0417": {
							"post": [1.39563, 2.88, 0],
							"lerp_mode": "catmullrom"
						},
						"1.375": {
							"post": [5.24, 2.88, 0],
							"lerp_mode": "catmullrom"
						},
						"1.7917": {
							"post": [1.04062, 2.88, 0],
							"lerp_mode": "catmullrom"
						},
						"1.8333": {
							"post": [1.39563, 2.88, 0],
							"lerp_mode": "catmullrom"
						},
						"2.0417": {
							"post": [1.39563, 2.88, 0],
							"lerp_mode": "catmullrom"
						},
						"2.4167": {
							"post": [1.4, 2.89563, -23],
							"lerp_mode": "catmullrom"
						},
						"2.75": {
							"post": [1.4, 2.9625, 0],
							"lerp_mode": "catmullrom"
						},
						"2.9167": {
							"post": [1.4, 2.7725, 0],
							"lerp_mode": "catmullrom"
						},
						"3.0417": {
							"post": [0, 1.625, 0],
							"lerp_mode": "catmullrom"
						},
						"3.2083": {
							"post": [0, 0, 0],
							"lerp_mode": "catmullrom"
						},
						"3.3333": {
							"post": [0, 1.625, 0],
							"lerp_mode": "catmullrom"
						},
						"3.5": {
							"post": [0, 0, 0],
							"lerp_mode": "catmullrom"
						},
						"3.7083": {
							"post": [0, 0, 0],
							"lerp_mode": "catmullrom"
						},
						"3.7917": {
							"post": [0, 1.625, 0],
							"lerp_mode": "catmullrom"
						},
						"3.875": {
							"post": [0, 0, 0],
							"lerp_mode": "catmullrom"
						},
						"4.2917": {
							"post": [10, 0, -24],
							"lerp_mode": "catmullrom"
						},
						"4.5833": {
							"post": [-11, 0, -24],
							"lerp_mode": "catmullrom"
						},
						"4.9583": {
							"post": [0, 0, 0],
							"lerp_mode": "catmullrom"
						},
						"5.2917": {
							"post": [10, 0, -24],
							"lerp_mode": "catmullrom"
						},
						"5.5833": {
							"post": [-11, 0, -24],
							"lerp_mode": "catmullrom"
						},
						"5.9583": {
							"post": [0, 0, 0],
							"lerp_mode": "catmullrom"
						},
						"6.2083": {
							"post": [0, 0, 0],
							"lerp_mode": "catmullrom"
						},
						"6.2917": {
							"post": [0, 1.625, 0],
							"lerp_mode": "catmullrom"
						},
						"6.375": {
							"post": [0, 0, 0],
							"lerp_mode": "catmullrom"
						},
						"6.7917": {
							"post": [0, 0, 0],
							"lerp_mode": "catmullrom"
						},
						"8.4583": {
							"post": [0, 0, 0],
							"lerp_mode": "catmullrom"
						}
					},
					"scale": {
						"0.0": {
							"post": [1, 1, 1],
							"lerp_mode": "catmullrom"
						}
					}
				},
				"left": {
					"rotation": {
						"0.0": [96.65895, 31.60263, 42.57262],
						"1.9167": [689.17756, 40.45561, 36.49954],
						"3.4583": [85, 0, 0],
						"4.75": [96.65895, 31.60263, 42.57262]
					},
					"position": {
						"0.0": [8, -12, -4],
						"0.8333": [-14.26, -26.65, -21],
						"1.9167": [36, 2, -29],
						"2.75": [42.74, -26.65, -21],
						"3.4583": [24, -16, 9],
						"4.75": [8, -12, -4]
					},
					"scale": {
						"0.0": [1, 1.5, 1],
						"4.75": [1, 1.5, 1]
					}
				},
				"right": {
					"rotation": {
						"0.0": [85, 0, 0],
						"1.7917": [689.17756, 40.45561, 36.49954],
						"3.3333": [85, 0, 0],
						"4.75": [85, 0, 0]
					},
					"position": {
						"0.0": [-6, -16, 9],
						"0.7083": [-14.26, -26.65, -21],
						"1.7917": [-19, -6, 9],
						"2.625": [-14.26, -26.65, -21],
						"3.3333": [-6, -16, 9],
						"4.75": [-6, -16, 9]
					},
					"scale": {
						"0.0": [1, 1.5, 1],
						"4.75": [1, 1.5, 1]
					}
				},
				"lefthand_and_mag": {
					"rotation": {
						"0.0": [0, 0, 0],
						"0.75": [0, -590, 0],
						"1.4167": [0, 0, 0],
						"2.1667": [0, -590, 0],
						"2.8333": [0, 0, 0],
						"3.5417": [0, -590, 0],
						"4.2083": [0, 0, 0],
						"4.7917": [0, -590, 0],
						"5.4583": [0, 0, 0],
						"6.0": [0, -590, 0],
						"6.6667": [0, 0, 0]
					}
				},
				"camera": {
					"rotation": [0, 0, 0]
				}
			},
			"sound_effects": {
				"0.0": {
					"effect": ".mp3"
				}
			}
		},
		"inspect_empty": {
			"loop": true,
			"animation_length": 9.2083,
			"bones": {
				"root": {
					"rotation": {
						"0.0": {
							"post": [0, 0, 2.5],
							"lerp_mode": "catmullrom"
						},
						"0.0417": {
							"post": [-776.14245, -14.25404, 1108.89135],
							"lerp_mode": "catmullrom"
						},
						"0.1667": {
							"post": [37.14529, -30.60802, -70.88992],
							"lerp_mode": "catmullrom"
						},
						"0.4167": {
							"post": [45.32384, -26.80832, -74.59681],
							"lerp_mode": "catmullrom"
						},
						"0.625": {
							"post": [-59.67616, -26.80832, -74.59681],
							"lerp_mode": "catmullrom"
						},
						"0.9583": {
							"post": [45.32384, -26.80832, -74.59681],
							"lerp_mode": "catmullrom"
						},
						"1.0": {
							"post": [-776.14245, -14.25404, 1108.89135],
							"lerp_mode": "catmullrom"
						},
						"1.0417": {
							"post": [45.32384, -26.80832, -74.59681],
							"lerp_mode": "catmullrom"
						},
						"1.0833": {
							"post": [-28.29773, 24.94219, 424.74059],
							"lerp_mode": "catmullrom"
						},
						"1.375": {
							"post": [-185.70715, 6.26262, 222.1569],
							"lerp_mode": "catmullrom"
						},
						"1.5833": {
							"post": [-41.46762, 48.91408, 21.23279],
							"lerp_mode": "catmullrom"
						},
						"1.7917": {
							"post": [-59.67616, -26.80832, -74.59681],
							"lerp_mode": "catmullrom"
						},
						"1.8333": {
							"post": [45.32384, -26.80832, -74.59681],
							"lerp_mode": "catmullrom"
						},
						"1.9583": {
							"post": [-31.56513, 37.21161, 32.94231],
							"lerp_mode": "catmullrom"
						},
						"2.0417": {
							"post": [45.32384, -26.80832, -74.59681],
							"lerp_mode": "catmullrom"
						},
						"2.1667": {
							"post": [-31.56513, 37.21161, 32.94231],
							"lerp_mode": "catmullrom"
						},
						"2.5417": {
							"post": [-26.36583, 19.55395, 43.87308],
							"lerp_mode": "catmullrom"
						},
						"2.75": {
							"post": [-28.91492, 30.36006, 37.71897],
							"lerp_mode": "catmullrom"
						},
						"2.9583": {
							"post": [43.58508, 30.36006, 37.71897],
							"lerp_mode": "catmullrom"
						},
						"3.0417": {
							"post": [-776.14245, -14.25404, 1108.89135],
							"lerp_mode": "catmullrom"
						},
						"3.2083": {
							"post": [0, 0, 2.5],
							"lerp_mode": "catmullrom"
						},
						"3.3333": {
							"post": [-776.14245, -14.25404, 1108.89135],
							"lerp_mode": "catmullrom"
						},
						"3.5": {
							"post": [0, 0, 2.5],
							"lerp_mode": "catmullrom"
						},
						"3.7083": {
							"post": [0, 0, 2.5],
							"lerp_mode": "catmullrom"
						},
						"3.7917": {
							"post": [-776.14245, -14.25404, 1108.89135],
							"lerp_mode": "catmullrom"
						},
						"3.875": {
							"post": [0, 0, 2.5],
							"lerp_mode": "catmullrom"
						},
						"4.25": {
							"post": [-180, -35, -177.5],
							"lerp_mode": "catmullrom"
						},
						"4.7083": {
							"post": [-657.5, 0, 2.5],
							"lerp_mode": "catmullrom"
						},
						"5.25": {
							"post": [-180, -35, -177.5],
							"lerp_mode": "catmullrom"
						},
						"5.7083": {
							"post": [0, 0, 2.5],
							"lerp_mode": "catmullrom"
						},
						"6.2083": {
							"post": [0, 0, 2.5],
							"lerp_mode": "catmullrom"
						},
						"6.2917": {
							"post": [-776.14245, -14.25404, 1108.89135],
							"lerp_mode": "catmullrom"
						},
						"6.375": {
							"post": [0, 0, 2.5],
							"lerp_mode": "catmullrom"
						},
						"6.5417": {
							"post": [0, 0, 2.5],
							"lerp_mode": "catmullrom"
						},
						"6.75": {
							"post": [-15, 0, 7.5],
							"lerp_mode": "catmullrom"
						},
						"7.2917": {
							"post": [0, 0, 2.5],
							"lerp_mode": "catmullrom"
						},
						"7.5833": {
							"post": [145.98062, 29.36734, 111.12959],
							"lerp_mode": "catmullrom"
						},
						"8.75": {
							"post": [0, 0, 2.5],
							"lerp_mode": "catmullrom"
						}
					},
					"position": {
						"0.0": {
							"post": [0, 0, 0],
							"lerp_mode": "catmullrom"
						},
						"0.0417": {
							"post": [0, 1.625, 0],
							"lerp_mode": "catmullrom"
						},
						"0.1667": {
							"post": [10.875, 2.88, -27],
							"lerp_mode": "catmullrom"
						},
						"0.4167": {
							"post": [1.39563, 2.88, 0],
							"lerp_mode": "catmullrom"
						},
						"0.625": {
							"post": [1.04062, 2.88, 0],
							"lerp_mode": "catmullrom"
						},
						"0.9583": {
							"post": [1.39563, 2.88, 0],
							"lerp_mode": "catmullrom"
						},
						"1.0": {
							"post": [0, 1.625, 0],
							"lerp_mode": "catmullrom"
						},
						"1.0417": {
							"post": [1.39563, 2.88, 0],
							"lerp_mode": "catmullrom"
						},
						"1.375": {
							"post": [5.24, 2.88, 0],
							"lerp_mode": "catmullrom"
						},
						"1.7917": {
							"post": [1.04062, 2.88, 0],
							"lerp_mode": "catmullrom"
						},
						"1.8333": {
							"post": [1.39563, 2.88, 0],
							"lerp_mode": "catmullrom"
						},
						"2.0417": {
							"post": [1.39563, 2.88, 0],
							"lerp_mode": "catmullrom"
						},
						"2.4167": {
							"post": [1.4, 2.89563, -23],
							"lerp_mode": "catmullrom"
						},
						"2.75": {
							"post": [1.4, 2.9625, 0],
							"lerp_mode": "catmullrom"
						},
						"2.9167": {
							"post": [1.4, 2.7725, 0],
							"lerp_mode": "catmullrom"
						},
						"3.0417": {
							"post": [0, 1.625, 0],
							"lerp_mode": "catmullrom"
						},
						"3.2083": {
							"post": [0, 0, 0],
							"lerp_mode": "catmullrom"
						},
						"3.3333": {
							"post": [0, 1.625, 0],
							"lerp_mode": "catmullrom"
						},
						"3.5": {
							"post": [0, 0, 0],
							"lerp_mode": "catmullrom"
						},
						"3.7083": {
							"post": [0, 0, 0],
							"lerp_mode": "catmullrom"
						},
						"3.7917": {
							"post": [0, 1.625, 0],
							"lerp_mode": "catmullrom"
						},
						"3.875": {
							"post": [0, 0, 0],
							"lerp_mode": "catmullrom"
						},
						"4.2917": {
							"post": [10, 0, -24],
							"lerp_mode": "catmullrom"
						},
						"4.5833": {
							"post": [-11, 0, -24],
							"lerp_mode": "catmullrom"
						},
						"4.9583": {
							"post": [0, 0, 0],
							"lerp_mode": "catmullrom"
						},
						"5.2917": {
							"post": [10, 0, -24],
							"lerp_mode": "catmullrom"
						},
						"5.5833": {
							"post": [-11, 0, -24],
							"lerp_mode": "catmullrom"
						},
						"5.9583": {
							"post": [0, 0, 0],
							"lerp_mode": "catmullrom"
						},
						"6.2083": {
							"post": [0, 0, 0],
							"lerp_mode": "catmullrom"
						},
						"6.2917": {
							"post": [0, 1.625, 0],
							"lerp_mode": "catmullrom"
						},
						"6.375": {
							"post": [0, 0, 0],
							"lerp_mode": "catmullrom"
						},
						"6.7917": {
							"post": [0, 0, 0],
							"lerp_mode": "catmullrom"
						},
						"8.4583": {
							"post": [0, 0, 0],
							"lerp_mode": "catmullrom"
						}
					},
					"scale": {
						"0.0": {
							"post": [1, 1, 1],
							"lerp_mode": "catmullrom"
						}
					}
				},
				"left": {
					"rotation": {
						"0.0": [96.65895, 31.60263, 42.57262],
						"1.9167": [689.17756, 40.45561, 36.49954],
						"3.4583": [85, 0, 0],
						"4.75": [96.65895, 31.60263, 42.57262]
					},
					"position": {
						"0.0": [8, -12, -4],
						"0.8333": [-14.26, -26.65, -21],
						"1.9167": [36, 2, -29],
						"2.75": [42.74, -26.65, -21],
						"3.4583": [24, -16, 9],
						"4.75": [8, -12, -4]
					},
					"scale": {
						"0.0": [1, 1.5, 1],
						"4.75": [1, 1.5, 1]
					}
				},
				"right": {
					"rotation": {
						"0.0": [85, 0, 0],
						"1.7917": [689.17756, 40.45561, 36.49954],
						"3.3333": [85, 0, 0],
						"4.75": [85, 0, 0]
					},
					"position": {
						"0.0": [-6, -16, 9],
						"0.7083": [-14.26, -26.65, -21],
						"1.7917": [-19, -6, 9],
						"2.625": [-14.26, -26.65, -21],
						"3.3333": [-6, -16, 9],
						"4.75": [-6, -16, 9]
					},
					"scale": {
						"0.0": [1, 1.5, 1],
						"4.75": [1, 1.5, 1]
					}
				},
				"lefthand_and_mag": {
					"rotation": {
						"0.0": [0, 0, 0],
						"0.75": [0, -590, 0],
						"1.4167": [0, 0, 0],
						"2.1667": [0, -590, 0],
						"2.8333": [0, 0, 0],
						"3.5417": [0, -590, 0],
						"4.2083": [0, 0, 0],
						"4.7917": [0, -590, 0],
						"5.4583": [0, 0, 0],
						"6.0": [0, -590, 0],
						"6.6667": [0, 0, 0]
					}
				},
				"camera": {
					"rotation": [0, 0, 0]
				}
			},
			"sound_effects": {
				"0.0": {
					"effect": ".mp3"
				}
			}
		},
		"static_bolt_caught": {
			"loop": true
		},
		"shoot": {
			"loop": true,
			"animation_length": 0.6667,
			"bones": {
				"root": {
					"rotation": {
						"0.0": {
							"post": [0, 0, 0],
							"lerp_mode": "catmullrom"
						},
						"0.0333": {
							"post": [0.24839, 0.0283, -6.49994],
							"lerp_mode": "catmullrom"
						},
						"0.0667": {
							"post": [-2.75049, 0.00873, 3.99939],
							"lerp_mode": "catmullrom"
						},
						"0.1": {
							"post": [-2.16351, -0.12391, -1.41431],
							"lerp_mode": "catmullrom"
						},
						"0.1667": {
							"post": [-0.9984, 0.06651, 0.74977],
							"lerp_mode": "catmullrom"
						},
						"0.2667": {
							"post": [0.37499, -0.00327, 0.24998],
							"lerp_mode": "catmullrom"
						},
						"0.4": {
							"post": [-0.135, 0, -0.18],
							"lerp_mode": "catmullrom"
						},
						"0.5333": [0.125, 0, 0],
						"0.6667": [0, 0, 0]
					},
					"position": {
						"0.0": {
							"post": [0, 0, 0],
							"lerp_mode": "catmullrom"
						},
						"0.0333": {
							"post": [0, -0.3, 1.65],
							"lerp_mode": "catmullrom"
						},
						"0.0667": {
							"post": [0, 0.075, 1.455],
							"lerp_mode": "catmullrom"
						},
						"0.1333": {
							"post": [0, 0.0375, -0.325],
							"lerp_mode": "catmullrom"
						},
						"0.2333": {
							"post": [0, -0.0625, -0.075],
							"lerp_mode": "catmullrom"
						},
						"0.3667": {
							"post": [0, -0.0625, 0.03125],
							"lerp_mode": "catmullrom"
						},
						"0.5333": [0, 0, 0],
						"0.6667": [0, 0, 0]
					}
				},
				"left": {
					"rotation": {
						"0.0": [0, 0, 0],
						"0.0667": [802.5, 842.5, 830],
						"0.1333": [0, 0, 0]
					}
				},
				"bolt": {
					"position": {
						"0.0": [0, 0, 0],
						"0.0333": [0, 0, 4.725],
						"0.0667": [0, 0, 0]
					}
				},
				"bullet_in_barrel": {
					"scale": {
						"0.0": [0, 0, 0],
						"0.2333": {"pre": [0, 0, 0], "post": [1, 1, 1]}
					}
				},
				"right": {
					"rotation": {
						"0.0": [0, 0, 0],
						"0.0667": [802.5, 842.5, 830],
						"0.1333": [0, 0, 0]
					}
				}
			}
		}
	}
}